jupyterlab_scicap_ui/__init__.py
jupyterlab_scicap_ui/_version.py
jupyterlab_scicap_ui/handlers.py
jupyterlab_scicap_ui-0.3.14.data/data/etc/jupyter/jupyter_server_config.d/jupyterlab_scicap_ui.json
jupyterlab_scicap_ui-0.3.14.data/data/share/jupyter/labextensions/@codytodonnell/jupyterlab-scicap-ui/build_log.json
jupyterlab_scicap_ui-0.3.14.data/data/share/jupyter/labextensions/@codytodonnell/jupyterlab-scicap-ui/package.json
jupyterlab_scicap_ui-0.3.14.data/data/share/jupyter/labextensions/@codytodonnell/jupyterlab-scicap-ui/static/3c23eb02de6b34e30f18cfb7167abd81a2cedfd1da60dfcb71989517ab3fb431.woff2
jupyterlab_scicap_ui-0.3.14.data/data/share/jupyter/labextensions/@codytodonnell/jupyterlab-scicap-ui/static/b7ef2cd1159a8cbfd271ff2abe07f237a46f6fa056eefd2e9018661f93eea137.woff2
jupyterlab_scicap_ui-0.3.14.data/data/share/jupyter/labextensions/@codytodonnell/jupyterlab-scicap-ui/static/e41533d5c6eab361631aa3cf8bf7b8a2e6babfcc42a1aa950b2b0cd80c109b8f.woff
jupyterlab_scicap_ui-0.3.14.data/data/share/jupyter/labextensions/@codytodonnell/jupyterlab-scicap-ui/static/f6734f8177112c0839b961f96d813fcb189d81b60e96c33278c1983b6f419615.woff2
jupyterlab_scicap_ui-0.3.14.data/data/share/jupyter/labextensions/@codytodonnell/jupyterlab-scicap-ui/static/lib_index_js.ff496f411d5cf893e908.js
jupyterlab_scicap_ui-0.3.14.data/data/share/jupyter/labextensions/@codytodonnell/jupyterlab-scicap-ui/static/lib_index_js.ff496f411d5cf893e908.js.map
jupyterlab_scicap_ui-0.3.14.data/data/share/jupyter/labextensions/@codytodonnell/jupyterlab-scicap-ui/static/remoteEntry.aeaf50afb798ed34751d.js
jupyterlab_scicap_ui-0.3.14.data/data/share/jupyter/labextensions/@codytodonnell/jupyterlab-scicap-ui/static/remoteEntry.aeaf50afb798ed34751d.js.map
jupyterlab_scicap_ui-0.3.14.data/data/share/jupyter/labextensions/@codytodonnell/jupyterlab-scicap-ui/static/style.js
jupyterlab_scicap_ui-0.3.14.dist-info/METADATA
jupyterlab_scicap_ui-0.3.14.dist-info/WHEEL
jupyterlab_scicap_ui-0.3.14.dist-info/licenses/LICENSE
jupyterlab_scicap_ui-0.3.14.dist-info/RECORD
